pytei/__init__.py
pytei/client.py
pytei/model.py
pytei/store.py
pytei_client-0.1.0.dist-info/LICENSE.md
pytei_client-0.1.0.dist-info/METADATA
pytei_client-0.1.0.dist-info/WHEEL
pytei_client-0.1.0.dist-info/top_level.txt
pytei_client-0.1.0.dist-info/RECORD
