Metadata-Version: 2.2
Name: pytei-client
Version: 0.1.0
Summary: Minimal wrapper for Hugging Face's Text Embeddings Inference.
Author-email: Daniel Gomm <daniel.gomm@cwi.nl>
Project-URL: Homepage, https://github.com/daniel-gomm/PyTEI
Project-URL: Issues, https://github.com/daniel-gomm/PyTEI/issues
Project-URL: Documentation, https://daniel-gomm.github.io/PyTEI/
Classifier: Programming Language :: Python :: 3
Classifier: Operating System :: OS Independent
Requires-Python: >=3.5
License-File: LICENSE.md
Requires-Dist: duckdb>=1.1.3
Requires-Dist: requests>=2.32.3
Requires-Dist: numpy>=2.2.1
